twitter_text/__init__.py
twitter_text/config.py
twitter_text/extract_emojis.py
twitter_text/extract_urls.py
twitter_text/get_character_weight.py
twitter_text/has_invalid_characters.py
twitter_text/parse_tweet.py
twitter_text/regex_supplant.py
twitter_text/regexp/__init__.py
twitter_text/regexp/cyrillic_letters_and_marks.py
twitter_text/regexp/directional_markers_group.py
twitter_text/regexp/emoji-test.txt
twitter_text/regexp/emoji.py
twitter_text/regexp/extract_url.py
twitter_text/regexp/invalid_chars.py
twitter_text/regexp/invalid_chars_group.py
twitter_text/regexp/invalid_domain_chars.py
twitter_text/regexp/invalid_url_without_protocol_preceding_chars.py
twitter_text/regexp/latin_accent_chars.py
twitter_text/regexp/punct.py
twitter_text/regexp/spaces_group.py
twitter_text/regexp/valid_ascii_domain.py
twitter_text/regexp/valid_cctld.py
twitter_text/regexp/valid_domain.py
twitter_text/regexp/valid_domain_chars.py
twitter_text/regexp/valid_domain_name.py
twitter_text/regexp/valid_general_url_path_chars.py
twitter_text/regexp/valid_gtld.py
twitter_text/regexp/valid_port_number.py
twitter_text/regexp/valid_punycode.py
twitter_text/regexp/valid_subdomain.py
twitter_text/regexp/valid_tco_url.py
twitter_text/regexp/valid_url_balanced_parens.py
twitter_text/regexp/valid_url_path.py
twitter_text/regexp/valid_url_path_ending_chars.py
twitter_text/regexp/valid_url_preceding_chars.py
twitter_text/regexp/valid_url_query_chars.py
twitter_text/regexp/valid_url_query_ending_chars.py
twitter_text_parser-3.0.0.dist-info/LICENSE
twitter_text_parser-3.0.0.dist-info/METADATA
twitter_text_parser-3.0.0.dist-info/WHEEL
twitter_text_parser-3.0.0.dist-info/RECORD
