Metadata-Version: 2.1
Name: twitter-text-parser
Version: 3.0.0
Summary: A library to parse or validate Twitter texts properly
Home-page: https://github.com/swen128/twitter-text-python
Author: swen128
Author-email: fujjisaaan@gmail.com
Requires-Python: >=3.7,<4.0
Classifier: Intended Audience :: Developers
Classifier: License :: OSI Approved :: MIT License
Classifier: Operating System :: OS Independent
Classifier: Programming Language :: Python :: 3
Classifier: Programming Language :: Python :: 3.7
Classifier: Programming Language :: Python :: 3.8
Classifier: Programming Language :: Python :: 3.9
Classifier: Programming Language :: Python :: 3.10
Classifier: Programming Language :: Python :: 3.11
Classifier: Topic :: Text Processing
Project-URL: Repository, https://github.com/swen128/twitter-text-python
